vec_utils_py-0.3.0.dist-info/METADATA
vec_utils_py-0.3.0.dist-info/WHEEL
vec_utils_py-0.3.0.dist-info/licenses/LICENSE
vec_utils_py.libs/libgcc_s-262c4f60.so.1
vec_utils_py/__init__.py
vec_utils_py/__init__.pyi
vec_utils_py/geometry/__init__.pyi
vec_utils_py/py.typed
vec_utils_py/vec_utils_py.cpython-313t-arm-linux-musleabihf.so
vec_utils_py-0.3.0.dist-info/RECORD
