Metadata-Version: 2.4
Name: vec-utils-py
Version: 0.3.0
Classifier: Programming Language :: Python :: 3
Classifier: Programming Language :: Rust
Classifier: Topic :: Scientific/Engineering :: Mathematics
Classifier: Operating System :: OS Independent
License-File: LICENSE
Summary: A simple vector operations library
Author-email: Akari202 <akaritwo0two@gmail.com>
License-Expression: GPL-3.0-only
Requires-Python: >=3.9
Project-URL: GitHub, https://github.com/Akari202/vec-utils
Project-URL: Issues, https://github.com/Akari202/vec-utils/issues
